rloop-0.2.0.dist-info/METADATA
rloop-0.2.0.dist-info/WHEEL
rloop-0.2.0.dist-info/licenses/LICENSE
rloop.libs/libgcc_s-0366c7ba.so.1
rloop/__init__.py
rloop/_compat.py
rloop/_rloop.cpython-314-arm-linux-musleabihf.so
rloop/_rloop.pyi
rloop/exc.py
rloop/futures.py
rloop/loop.py
rloop/server.py
rloop/subprocess.py
rloop/transports.py
rloop/utils.py
rloop-0.2.0.dist-info/RECORD
