Metadata-Version: 2.4
Name: rloop
Version: 0.2.0
Classifier: Development Status :: 3 - Alpha
Classifier: Intended Audience :: Developers
Classifier: License :: OSI Approved :: BSD License
Classifier: Operating System :: MacOS
Classifier: Operating System :: POSIX :: Linux
Classifier: Programming Language :: Python :: Free Threading :: 2 - Beta
Classifier: Programming Language :: Python :: 3
Classifier: Programming Language :: Python :: 3.9
Classifier: Programming Language :: Python :: 3.10
Classifier: Programming Language :: Python :: 3.11
Classifier: Programming Language :: Python :: 3.12
Classifier: Programming Language :: Python :: 3.13
Classifier: Programming Language :: Python :: Implementation :: CPython
Classifier: Programming Language :: Python :: Implementation :: PyPy
Classifier: Programming Language :: Python
Classifier: Programming Language :: Rust
License-File: LICENSE
Summary: An asyncio event loop implemented in Rust
Keywords: asyncio
Home-Page: https://github.com/gi0baro/rloop
Author-email: Giovanni Barillari <g@baro.dev>
License: BSD-3-Clause
Requires-Python: >=3.9
Project-URL: Homepage, https://github.com/gi0baro/rloop
Project-URL: Funding, https://github.com/sponsors/gi0baro
Project-URL: Source, https://github.com/gi0baro/rloop
